README.md
setup.py
local_environment/__init__.py
local_environment.egg-info/PKG-INFO
local_environment.egg-info/SOURCES.txt
local_environment.egg-info/dependency_links.txt
local_environment.egg-info/requires.txt
local_environment.egg-info/top_level.txt
local_environment/core/__init__.py
local_environment/core/base_async_builder.py
local_environment/core/base_builder.py
local_environment/core/builder_param.py
local_environment/dependencies/__init__.py
local_environment/dependencies/base_async_dependency.py
local_environment/dependencies/base_dependency.py
local_environment/dependencies/composites/__init__.py
local_environment/dependencies/composites/base_composite.py
local_environment/directors/__init__.py
local_environment/directors/async_environment_director.py
local_environment/directors/base_async_director.py
local_environment/directors/base_director.py
local_environment/directors/environment_director.py